setup.py
PyPi_SemanticVer.egg-info/PKG-INFO
PyPi_SemanticVer.egg-info/SOURCES.txt
PyPi_SemanticVer.egg-info/dependency_links.txt
PyPi_SemanticVer.egg-info/top_level.txt
bin/pip-sv
pipsv/__init__.py