Metadata-Version: 1.1
Name: PyPi-SemanticVer
Version: 0.1.0
Summary: A command line tool for incrementing semantic versioning 
Home-page: UNKNOWN
Author: John Brunelle
Author-email: devjohnb@gmail.com
License: MIT
Platform: UNKNOWN
Classifier: Development Status :: 3 - Alpha
Classifier: Programming Language :: Python
Classifier: Programming Language :: Python :: 3.6
